pySpeechAlien/__init__.py
pySpeechAlien-2.1.dist-info/DESCRIPTION.rst
pySpeechAlien-2.1.dist-info/METADATA
pySpeechAlien-2.1.dist-info/RECORD
pySpeechAlien-2.1.dist-info/WHEEL
pySpeechAlien-2.1.dist-info/metadata.json
pySpeechAlien-2.1.dist-info/top_level.txt
