Metadata-Version: 2.0
Name: pySpeechAlien
Version: 2.1
Summary: Speech analysis tool
Home-page: https://github.com/arpansahoo/pySpeechAlien
Author: Arpan Sahoo
Author-email: asahoo1@jhu.edu
License: MIT
Keywords: praat speech-analysis python
Platform: UNKNOWN
Classifier: Programming Language :: Python :: 2.7
Classifier: Programming Language :: Python :: 3
Classifier: License :: OSI Approved :: MIT License
Classifier: Operating System :: OS Independent
Requires-Dist: numpy (>=1.15.2)
Requires-Dist: praat-parselmouth (>=0.3.2)
Requires-Dist: pandas (>=0.23.4)
Requires-Dist: scipy (>=1.1.0)
